Metadata-Version: 2.1
Name: yay-automation
Version: 1.1.2
Summary: yay!というSNSに使えるAPIラッパー
Home-page: https://github.com/taka-4602/yay-automation
Author: taka4602
Author-email: shun4602@gmail.com
Keywords: yay
Classifier: Programming Language :: Python :: 3
Classifier: License :: OSI Approved :: MIT License
Classifier: Operating System :: OS Independent
Requires-Python: >=3.6
